napari_plugin_test_ferrinm/__init__.py
napari_plugin_test_ferrinm/_version.py
napari_plugin_test_ferrinm/_widget.py
napari_plugin_test_ferrinm/napari.yaml
napari_plugin_test_ferrinm-0.6.0.dist-info/licenses/LICENSE
napari_plugin_test_ferrinm-0.6.0.dist-info/METADATA
napari_plugin_test_ferrinm-0.6.0.dist-info/WHEEL
napari_plugin_test_ferrinm-0.6.0.dist-info/entry_points.txt
napari_plugin_test_ferrinm-0.6.0.dist-info/top_level.txt
napari_plugin_test_ferrinm-0.6.0.dist-info/RECORD
