Metadata-Version: 2.4
Name: napari-plugin-test-ferrinm
Version: 0.6.0
Summary: testing plugin publishing
Author: Max Ferrin
Author-email: ferrinmax@gmail.com
License: 
Project-URL: Bug Tracker, https://github.com/ferrinm/napari-plugin-test-ferrinm/issues
Project-URL: Documentation, https://github.com/ferrinm/napari-plugin-test-ferrinm#README.md
Project-URL: Source Code, https://github.com/ferrinm/napari-plugin-test-ferrinm
Project-URL: User Support, https://github.com/ferrinm/napari-plugin-test-ferrinm/issues
Classifier: Development Status :: 2 - Pre-Alpha
Classifier: Framework :: napari
Classifier: Intended Audience :: Developers
Classifier: License :: OSI Approved :: BSD License
Classifier: Operating System :: OS Independent
Classifier: Programming Language :: Python
Classifier: Programming Language :: Python :: 3
Classifier: Programming Language :: Python :: 3 :: Only
Classifier: Programming Language :: Python :: 3.10
Classifier: Programming Language :: Python :: 3.11
Classifier: Programming Language :: Python :: 3.12
Classifier: Programming Language :: Python :: 3.13
Classifier: Topic :: Scientific/Engineering :: Image Processing
Requires-Python: >=3.10
License-File: LICENSE
Requires-Dist: numpy
Requires-Dist: magicgui
Requires-Dist: qtpy
Requires-Dist: scikit-image
Provides-Extra: all
Requires-Dist: napari[all]; extra == "all"
Dynamic: license-file
